igc2kml/__init__.py
igc2kml/color_maps.py
igc2kml/igc2kml.py
igc2kml/launch_sites.py
igc2kml-0.1.0.dist-info/METADATA
igc2kml-0.1.0.dist-info/WHEEL
igc2kml-0.1.0.dist-info/entry_points.txt
igc2kml-0.1.0.dist-info/licenses/LICENSE
igc2kml-0.1.0.dist-info/RECORD
