Metadata-Version: 2.3
Name: igc2kml
Version: 0.1.0
Summary: Convert IGC files from glider flights to KML files, which can be viewed in Google Earth.
License-File: LICENSE
Requires-Python: >=3.7
